httpgo-0.30.0.dist-info/METADATA
httpgo-0.30.0.dist-info/WHEEL
httpgo-0.30.0.dist-info/entry_points.txt
httpgo/__init__.py
httpgo/__version__.py
httpgo/main.py
httpgo/utils/__init__.py
httpgo/utils/_callback.py
httpgo/utils/_enum.py
httpgo/utils/_exception.py
httpgo/utils/_type.py
httpgo-0.30.0.dist-info/RECORD
